django_elastic_migrations
