Metadata-Version: 1.1
Name: django-elastic-migrations
Version: 0.8.2
Summary: Manage Elasticsearch Indexes in Django
Home-page: https://github.com/HBS-HBX/django-elastic-migrations
Author: Harvard Business School, HBX Department
Author-email: pnore@hbs.edu
License: MIT
Keywords: Django Elasticsearch
Platform: UNKNOWN
Classifier: Development Status :: 4 - Beta
Classifier: Framework :: Django
Classifier: Framework :: Django :: 1.9
Classifier: Framework :: Django :: 1.10
Classifier: Framework :: Django :: 1.11
Classifier: Framework :: Django :: 2.0
Classifier: Intended Audience :: Developers
Classifier: License :: OSI Approved :: MIT License
Classifier: Natural Language :: English
Classifier: Programming Language :: Python :: 3
Classifier: Programming Language :: Python :: 3.6
